outer/Dir.py
outer/File.py
outer/__init__.py
outer/core/Path.py
outer/core/PathType.py
outer/core/__init__.py
outer/demo/BluePrintSample.py
outer/demo/__init__.py
outer/demo/out_blueprint_test.py
outer-1.3.dist-info/LICENSE
outer-1.3.dist-info/METADATA
outer-1.3.dist-info/WHEEL
outer-1.3.dist-info/top_level.txt
outer-1.3.dist-info/RECORD
